package_mallah/__init__.py
package_mallah/annee_bissextille.py
package_mallah/table_multiplication.py
package_mallah-0.0.1.dist-info/LICENCE.txt
package_mallah-0.0.1.dist-info/METADATA
package_mallah-0.0.1.dist-info/WHEEL
package_mallah-0.0.1.dist-info/top_level.txt
package_mallah-0.0.1.dist-info/RECORD
