Metadata-Version: 2.1
Name: package-mallah
Version: 0.0.1
Summary: Package with two modules
Home-page: UNKNOWN
Author: Mallah Cherif
Author-email: shadowalkersw1@gmail.com
License: UNKNOWN
Keywords: modules
Platform: UNKNOWN
Classifier: Development Status :: 5 - Production/Stable
Classifier: Intended Audience :: Education
Classifier: Operating System :: Microsoft :: Windows :: Windows 10
Classifier: License :: OSI Approved :: MIT License
Classifier: Programming Language :: Python :: 3
